nstbrowser/__init__.py
nstbrowser/_version.py
nstbrowser/client.py
nstbrowser/services/__init__.py
nstbrowser/services/_base.py
nstbrowser/services/browsers.py
nstbrowser/services/cdp_endpoints.py
nstbrowser/services/locals.py
nstbrowser/services/profiles.py
nstbrowser-0.0.3.dist-info/licenses/LICENSE
tests/__init__.py
tests/test_client.py
nstbrowser-0.0.3.dist-info/METADATA
nstbrowser-0.0.3.dist-info/WHEEL
nstbrowser-0.0.3.dist-info/top_level.txt
nstbrowser-0.0.3.dist-info/RECORD
