Metadata-Version: 2.4
Name: nstbrowser
Version: 0.0.3
Summary: nstbrowser python sdk
Home-page: https://github.com/Nstbrowser/nstbrowser-sdk-python
Author: nstbrowser
Author-email: nstbrowser@gmail.com
License: MIT
Project-URL: Documentation, https://github.com/Nstbrowser/nstbrowser-sdk-python#readme
Project-URL: Source, https://github.com/Nstbrowser/nstbrowser-sdk-python
Keywords: nstbrowser,nstbrowser-sdk,nstbrowser-sdk-python,nst,nst-sdk,nst-sdk-python,nstlabs
Classifier: License :: OSI Approved :: MIT License
Classifier: Operating System :: OS Independent
Classifier: Programming Language :: Python
Classifier: Programming Language :: Python :: 3
Classifier: Programming Language :: Python :: 3.6
Classifier: Programming Language :: Python :: 3.7
Classifier: Programming Language :: Python :: 3.8
Classifier: Programming Language :: Python :: 3.9
Classifier: Topic :: Internet :: WWW/HTTP :: Browsers
Classifier: Topic :: Software Development :: Libraries :: Python Modules
Requires-Python: >=3.6
License-File: LICENSE
Requires-Dist: requests
Dynamic: author
Dynamic: author-email
Dynamic: classifier
Dynamic: description
Dynamic: description-content-type
Dynamic: home-page
Dynamic: keywords
Dynamic: license
Dynamic: license-file
Dynamic: project-url
Dynamic: requires-dist
Dynamic: requires-python
Dynamic: summary
